rotalabs_probe/__init__.py
rotalabs_probe/_version.py
rotalabs_probe/analyzers/__init__.py
rotalabs_probe/analyzers/base.py
rotalabs_probe/analyzers/counterfactual_cot.py
rotalabs_probe/analyzers/model_api.py
rotalabs_probe/detectors/__init__.py
rotalabs_probe/detectors/base.py
rotalabs_probe/detectors/observer_effect.py
rotalabs_probe/detectors/sandbagging_detector.py
rotalabs_probe/detectors/situational_awareness.py
rotalabs_probe/integrations/__init__.py
rotalabs_probe/integrations/anthropic_api.py
rotalabs_probe/integrations/base.py
rotalabs_probe/integrations/openai_api.py
rotalabs_probe/probing/__init__.py
rotalabs_probe/probing/extraction.py
rotalabs_probe/probing/hooks.py
rotalabs_probe/probing/probes.py
rotalabs_probe/probing/vectors.py
rotalabs_probe/utils/__init__.py
rotalabs_probe/utils/feature_extraction.py
rotalabs_probe/utils/statistical_tests.py
rotalabs_probe/utils/text_processing.py
rotalabs_probe/viz/__init__.py
rotalabs_probe/viz/plotting.py
rotalabs_probe-1.0.0.dist-info/METADATA
rotalabs_probe-1.0.0.dist-info/WHEEL
rotalabs_probe-1.0.0.dist-info/licenses/LICENSE
rotalabs_probe-1.0.0.dist-info/RECORD
