Metadata-Version: 2.4
Name: rotalabs-probe
Version: 1.0.0
Summary: Sandbagging detection via activation probes - Detects when AI systems deliberately underperform
Project-URL: Homepage, https://rotalabs.ai
Project-URL: Repository, https://github.com/rotalabs/rotalabs-probe
Project-URL: Documentation, https://rotalabs.github.io/rotalabs-probe/
Author-email: Subhadip Mitra <subhadip@rotalabs.ai>, Rotalabs Research <research@rotalabs.ai>
License-Expression: AGPL-3.0-or-later
License-File: LICENSE
Keywords: activation-probing,ai-safety,llm-security,metacognition,sandbagging-detection,situational-awareness
Classifier: Development Status :: 4 - Beta
Classifier: Intended Audience :: Developers
Classifier: Intended Audience :: Science/Research
Classifier: License :: OSI Approved :: GNU Affero General Public License v3 or later (AGPLv3+)
Classifier: Programming Language :: Python :: 3
Classifier: Programming Language :: Python :: 3.9
Classifier: Programming Language :: Python :: 3.10
Classifier: Programming Language :: Python :: 3.11
Classifier: Programming Language :: Python :: 3.12
Classifier: Topic :: Scientific/Engineering :: Artificial Intelligence
Classifier: Topic :: Security
Requires-Python: >=3.9
Requires-Dist: numpy>=1.24.0
Requires-Dist: pandas>=2.0.0
Requires-Dist: scipy>=1.10.0
Provides-Extra: all
Requires-Dist: anthropic>=0.18.0; extra == 'all'
Requires-Dist: matplotlib>=3.7.0; extra == 'all'
Requires-Dist: openai>=1.0.0; extra == 'all'
Requires-Dist: scikit-learn>=1.3.0; extra == 'all'
Requires-Dist: seaborn>=0.12.0; extra == 'all'
Requires-Dist: torch>=2.0.0; extra == 'all'
Requires-Dist: transformers>=4.35.0; extra == 'all'
Provides-Extra: anthropic
Requires-Dist: anthropic>=0.18.0; extra == 'anthropic'
Provides-Extra: dev
Requires-Dist: black>=23.0.0; extra == 'dev'
Requires-Dist: mypy>=1.5.0; extra == 'dev'
Requires-Dist: pytest-asyncio>=0.21.0; extra == 'dev'
Requires-Dist: pytest-cov>=4.1.0; extra == 'dev'
Requires-Dist: pytest>=7.4.0; extra == 'dev'
Requires-Dist: ruff>=0.1.0; extra == 'dev'
Provides-Extra: docs
Requires-Dist: mkdocs-material>=9.4.0; extra == 'docs'
Requires-Dist: mkdocs>=1.5.0; extra == 'docs'
Requires-Dist: mkdocstrings[python]>=0.24.0; extra == 'docs'
Provides-Extra: gpu
Requires-Dist: scikit-learn>=1.3.0; extra == 'gpu'
Requires-Dist: torch>=2.0.0; extra == 'gpu'
Requires-Dist: transformers>=4.35.0; extra == 'gpu'
Provides-Extra: openai
Requires-Dist: openai>=1.0.0; extra == 'openai'
Provides-Extra: viz
Requires-Dist: matplotlib>=3.7.0; extra == 'viz'
Requires-Dist: seaborn>=0.12.0; extra == 'viz'
